discord_tts/__init__.py
discord_tts/core.py
discord_tts/exceptions.py
discord_tts/utils.py
discord_tts-0.1.0.dist-info/LICENSE
discord_tts-0.1.0.dist-info/METADATA
discord_tts-0.1.0.dist-info/WHEEL
discord_tts-0.1.0.dist-info/top_level.txt
discord_tts-0.1.0.dist-info/RECORD
