Metadata-Version: 2.1
Name: discord-tts
Version: 0.1.0
Summary: Discord 봇을 위한 TTS(Text-to-Speech) 라이브러리
Home-page: https://github.com/gksmfahd78/discord-tts
Author: gksmfahd78
Author-email: leedonghyun@kakao.com
Classifier: Programming Language :: Python :: 3
Classifier: License :: OSI Approved :: MIT License
Classifier: Operating System :: OS Independent
Requires-Python: >=3.8
License-File: LICENSE
Requires-Dist: discord.py >=2.0.0
Requires-Dist: gTTS >=2.3.1
Requires-Dist: PyNaCl >=1.4.0
